[
  {
    "title": "Tell us about you",
    "text": "Provide details about your property needs and financial situation"
  },
  {
    "title": "We shortlist options",
    "text": "Our smart tech compares thousands of options from 35+ lenders to match your needs."
  },
  {
    "title": "Upload your docs",
    "text": "Easily upload all required docs online. This means less paperwork!"
  },
  {
    "title": "Choose your loan",
    "text": "Our Approval Confidence™ tech only shows loans with a high approval likelihood."
  },
  {
    "title": "Settle your loan",
    "text": "Once you submit your application our team will keep you regularly updated on its progress."
  }
]
